{
  "posts": [
    {
      "slug": "/blog/container-queries",
      "title": "Como el CSS moderno te puede salvar la vida",
      "subtitle": "Guía rápida de las container queries",
      "date": "2024-02-26",
      "img": "assets/monstera.webp",
      "tags": [
        "css"
      ]
    },
    {
      "slug": "/blog/charli-lines",
      "title": "Larga vida a los filtros de instagram",
      "subtitle": "Tratamiento de imágenes en Javascript Canvas",
      "date": "2024-03-25",
      "img": "assets/posts/images/charli-lines.png",
      "tags": [
        "js",
        "canvas"
      ]
    },
    {
      "slug": "/blog/rustuino",
      "title": "Ns",
      "subtitle": "Compilando código de Rust en Arduino",
      "date": "2024-04-13",
      "img": "assets/posts/images/charli-lines.png",
      "tags": [
        "arduino",
        "rust",
        "softare embebido"
      ]
    }
  ]
}